.coveragerc
.editorconfig
.gitignore
.travis.yml
LICENSE
README.md
pyproject.toml
requirements.txt
requirements_dev.txt
setup.cfg
setup.py
.github/workflows/python-publish.yml
democritus_html/__init__.py
democritus_html/html_data.py
democritus_html/html_data_temp_utils.py
democritus_html.egg-info/PKG-INFO
democritus_html.egg-info/SOURCES.txt
democritus_html.egg-info/dependency_links.txt
democritus_html.egg-info/requires.txt
democritus_html.egg-info/top_level.txt
democritus_html.egg-info/zip-safe
tests/__init__.py
tests/test_html_data.py